gblurs.py
gblurs-9.dist-info/METADATA
gblurs-9.dist-info/WHEEL
gblurs-9.dist-info/top_level.txt
gblurs-9.dist-info/RECORD
