Metadata-Version: 2.4
Name: gblurs
Version: 9
Summary: All Gaussian Blurs
Author: Enric Meinhardt-Llopis
Author-email: enric.meinhardt@fastmail.com
Classifier: Operating System :: OS Independent
Classifier: Topic :: Scientific/Engineering :: Image Processing
Classifier: Topic :: Scientific/Engineering :: Mathematics
Dynamic: author
Dynamic: author-email
Dynamic: classifier
Dynamic: summary
